{
  "core": {
    "core": {
      "red": {
        "50": {
          "value": "#FDE7E2",
          "type": "color"
        },
        "100": {
          "value": "#FFCBC0",
          "type": "color"
        },
        "200": {
          "value": "#F7856E",
          "type": "color"
        },
        "300": {
          "value": "#F67055",
          "type": "color"
        },
        "400": {
          "value": "#F65836",
          "type": "color"
        },
        "500": {
          "value": "#D44527",
          "type": "color"
        },
        "600": {
          "value": "#A3331A",
          "type": "color"
        },
        "700": {
          "value": "#772513",
          "type": "color"
        },
        "800": {
          "value": "#581C0E",
          "type": "color"
        },
        "900": {
          "value": "#351008",
          "type": "color"
        }
      },
      "neutral": {
        "50": {
          "value": "#FFFFFF",
          "type": "color"
        },
        "100": {
          "value": "#FAFAFA",
          "type": "color"
        },
        "200": {
          "value": "#F1F3F4",
          "type": "color"
        },
        "300": {
          "value": "#EDEDED",
          "type": "color"
        },
        "400": {
          "value": "#D9D9D9",
          "type": "color"
        },
        "500": {
          "value": "#CCCCCC",
          "type": "color"
        },
        "600": {
          "value": "#A6A6A6",
          "type": "color"
        },
        "700": {
          "value": "#656565",
          "type": "color"
        },
        "800": {
          "value": "#4D4D4D",
          "type": "color"
        },
        "900": {
          "value": "#262626",
          "type": "color"
        }
      },
      "space": {
        "half": {
          "value": "{core.space.base}*0.5",
          "type": "spacing",
          "description": "2px"
        },
        "base": {
          "value": "0.25rem",
          "type": "spacing",
          "description": "4px"
        },
        "2x": {
          "value": "{core.space.base} * 2",
          "type": "spacing",
          "description": "8px"
        },
        "3x": {
          "value": "{core.space.base} * 3",
          "type": "spacing",
          "description": "12px"
        },
        "4x": {
          "value": "{core.space.base}*4",
          "type": "spacing",
          "description": "16px"
        },
        "5x": {
          "value": "{core.space.base} * 5",
          "type": "spacing",
          "description": "20px"
        },
        "6x": {
          "value": "{core.space.base}*6",
          "type": "spacing",
          "description": "24px"
        },
        "8x": {
          "value": "{core.space.base}*8",
          "type": "spacing",
          "description": "32px"
        },
        "10x": {
          "value": "{core.space.base}*10",
          "type": "spacing",
          "description": "40px"
        },
        "12x": {
          "value": "{core.space.base}*12",
          "type": "spacing",
          "description": "48px"
        },
        "16x": {
          "value": "{core.space.base}*16",
          "type": "spacing",
          "description": "64px\n"
        },
        "18x": {
          "value": "{core.space.base}*18",
          "type": "spacing",
          "description": "72px"
        },
        "20x": {
          "value": "{core.space.base}*20",
          "type": "spacing",
          "description": "80px\n"
        },
        "26x": {
          "value": "{core.space.base}*26",
          "type": "spacing",
          "description": "104px"
        },
        "45x": {
          "value": "{core.space.base}*45",
          "type": "spacing",
          "description": "180px"
        },
        "60x": {
          "value": "{core.space.base}*60",
          "type": "spacing",
          "description": "240px"
        }
      },
      "radius": {
        "none": {
          "value": "0rem",
          "type": "borderRadius",
          "description": "0px"
        },
        "xxs": {
          "value": "0.125rem",
          "type": "borderRadius",
          "description": "2px"
        },
        "xsm": {
          "value": "0.25rem",
          "type": "borderRadius",
          "description": "4px"
        },
        "sm": {
          "value": "0.5",
          "type": "borderRadius",
          "description": "8px"
        },
        "md": {
          "value": "1rem",
          "type": "borderRadius",
          "description": "16px"
        },
        "lg": {
          "value": "1.5rem",
          "type": "borderRadius",
          "description": "24px"
        },
        "xlg": {
          "value": "2rem",
          "type": "borderRadius",
          "description": "32px"
        },
        "xxlg": {
          "value": "2.25rem",
          "type": "borderRadius",
          "description": "36px"
        },
        "max": {
          "value": "300px",
          "type": "borderRadius",
          "description": "100%"
        }
      },
      "elevation": {
        "0": {
          "value": {
            "x": "0",
            "y": "0",
            "blur": "0",
            "spread": "0",
            "color": "#000000",
            "type": "dropShadow"
          },
          "type": "boxShadow"
        },
        "50": {
          "value": [
            {
              "color": "rgba(38,38,38,0.1)",
              "type": "dropShadow",
              "x": "0",
              "y": "1",
              "blur": "3",
              "spread": "0"
            },
            {
              "color": "rgba(38,38,38,0.1)",
              "type": "dropShadow",
              "x": "0",
              "y": "0",
              "blur": "1",
              "spread": "0"
            }
          ],
          "type": "boxShadow"
        },
        "100": {
          "value": [
            {
              "color": "rgba(38,38,38,0.1)",
              "type": "dropShadow",
              "x": "0",
              "y": "2",
              "blur": "4",
              "spread": "0"
            },
            {
              "color": "rgba(38,38,38,0.1)",
              "type": "dropShadow",
              "x": "0",
              "y": "0",
              "blur": "1",
              "spread": "0"
            }
          ],
          "type": "boxShadow"
        },
        "200": {
          "value": [
            {
              "color": "rgba(38,38,38,0.1)",
              "type": "dropShadow",
              "x": "0",
              "y": "4",
              "blur": "8",
              "spread": "0"
            },
            {
              "color": "rgba(38,38,38,0.1)",
              "type": "dropShadow",
              "x": "0",
              "y": "0",
              "blur": "1",
              "spread": "0"
            }
          ],
          "type": "boxShadow"
        },
        "300": {
          "value": [
            {
              "color": "rgba(38,38,38,0.1)",
              "type": "dropShadow",
              "x": "0",
              "y": "8",
              "blur": "16",
              "spread": "0"
            },
            {
              "color": "rgba(38,38,38,0.1)",
              "type": "dropShadow",
              "x": "0",
              "y": "0",
              "blur": "1",
              "spread": "0"
            }
          ],
          "type": "boxShadow"
        },
        "400": {
          "value": [
            {
              "color": "rgba(38,38,38,0.1)",
              "type": "dropShadow",
              "x": "0",
              "y": "16",
              "blur": "24",
              "spread": "0"
            },
            {
              "color": "rgba(38,38,38,0.1)",
              "type": "dropShadow",
              "x": "0",
              "y": "0",
              "blur": "1",
              "spread": "0"
            }
          ],
          "type": "boxShadow"
        }
      },
      "opacity": {
        "lighter": {
          "value": "25%",
          "type": "opacity"
        },
        "light": {
          "value": "35%",
          "type": "opacity"
        },
        "dark": {
          "value": "65%",
          "type": "opacity"
        },
        "darker": {
          "value": "90%",
          "type": "opacity"
        }
      },
      "green": {
        "50": {
          "value": "#D9E2CC",
          "type": "color"
        },
        "100": {
          "value": "#B2CBA3",
          "type": "color"
        },
        "200": {
          "value": "#82B37A",
          "type": "color"
        },
        "300": {
          "value": "#529A55",
          "type": "color"
        },
        "400": {
          "value": "#2A8042",
          "type": "color"
        },
        "500": {
          "value": "#036635",
          "type": "color"
        },
        "600": {
          "value": "#015B2E",
          "type": "color"
        },
        "700": {
          "value": "#004F28",
          "type": "color"
        },
        "800": {
          "value": "#004321",
          "type": "color"
        },
        "900": {
          "value": "#00371B",
          "type": "color"
        }
      },
      "orange": {
        "50": {
          "value": "#FFEF8C",
          "type": "color"
        },
        "100": {
          "value": "#FFDF70",
          "type": "color"
        },
        "200": {
          "value": "#FFCD54",
          "type": "color"
        },
        "300": {
          "value": "#FFB738",
          "type": "color"
        },
        "400": {
          "value": "#FF9E1C",
          "type": "color"
        },
        "500": {
          "value": "#FF8300",
          "type": "color"
        },
        "600": {
          "value": "#DF7300",
          "type": "color"
        },
        "700": {
          "value": "#BF6200",
          "type": "color"
        },
        "800": {
          "value": "#9F5200",
          "type": "color"
        },
        "900": {
          "value": "#804200",
          "type": "color"
        }
      },
      "blue": {
        "50": {
          "value": "#BFD9FF",
          "type": "color"
        },
        "100": {
          "value": "#99C8FF",
          "type": "color"
        },
        "200": {
          "value": "#73BCFE",
          "type": "color"
        },
        "300": {
          "value": "#4DB4FA",
          "type": "color"
        },
        "400": {
          "value": "#26AEF5",
          "type": "color"
        },
        "500": {
          "value": "#00ACEE",
          "type": "color"
        },
        "600": {
          "value": "#0097D0",
          "type": "color"
        },
        "700": {
          "value": "#0081B3",
          "type": "color"
        },
        "800": {
          "value": "#006C95",
          "type": "color"
        },
        "900": {
          "value": "#005677",
          "type": "color"
        }
      }
    },
    "fontFamilies": {
      "riforma-ll": {
        "value": "Riforma LL",
        "type": "fontFamilies"
      }
    },
    "lineHeights": {
      "0": {
        "value": "100%",
        "type": "lineHeights"
      },
      "1": {
        "value": "150%",
        "type": "lineHeights"
      }
    },
    "fontWeights": {
      "riforma-ll-0": {
        "value": "Bold",
        "type": "fontWeights"
      },
      "riforma-ll-1": {
        "value": "Regular",
        "type": "fontWeights"
      },
      "riforma-ll-2": {
        "value": "Medium",
        "type": "fontWeights"
      },
      "riforma-ll-3": {
        "value": "Light",
        "type": "fontWeights"
      }
    },
    "fontSize": {
      "0": {
        "value": "14",
        "type": "fontSizes"
      },
      "1": {
        "value": "16",
        "type": "fontSizes"
      },
      "2": {
        "value": "18",
        "type": "fontSizes"
      },
      "3": {
        "value": "20",
        "type": "fontSizes"
      },
      "4": {
        "value": "24",
        "type": "fontSizes"
      },
      "5": {
        "value": "36",
        "type": "fontSizes"
      },
      "6": {
        "value": "40",
        "type": "fontSizes"
      },
      "7": {
        "value": "64",
        "type": "fontSizes"
      },
      "8": {
        "value": "80",
        "type": "fontSizes"
      }
    },
    "letterSpacing": {
      "0": {
        "value": "-1%",
        "type": "letterSpacing"
      },
      "1": {
        "value": "0%",
        "type": "letterSpacing"
      },
      "2": {
        "value": "1%",
        "type": "letterSpacing"
      }
    },
    "paragraphSpacing": {
      "0": {
        "value": "0",
        "type": "paragraphSpacing"
      }
    },
    "textCase": {
      "none": {
        "value": "none",
        "type": "textCase"
      }
    },
    "textDecoration": {
      "none": {
        "value": "none",
        "type": "textDecoration"
      }
    },
    "paragraphIndent": {
      "0": {
        "value": "0px",
        "type": "dimension"
      }
    }
  },
  "Brand/Radius": {
    "LG Breakpoint": {
      "heading": {
        "xxl": {
          "value": {
            "fontFamily": "{fontFamilies.riforma-ll}",
            "fontWeight": "{fontWeights.riforma-ll-0}",
            "lineHeight": "{lineHeights.0}",
            "fontSize": "{fontSize.8}",
            "letterSpacing": "{letterSpacing.0}",
            "paragraphSpacing": "{paragraphSpacing.0}",
            "paragraphIndent": "{paragraphIndent.0}",
            "textCase": "{textCase.none}",
            "textDecoration": "{textDecoration.none}"
          },
          "type": "typography"
        },
        "xl": {
          "value": {
            "fontFamily": "{fontFamilies.riforma-ll}",
            "fontWeight": "{fontWeights.riforma-ll-0}",
            "lineHeight": "{lineHeights.0}",
            "fontSize": "{fontSize.6}",
            "letterSpacing": "{letterSpacing.0}",
            "paragraphSpacing": "{paragraphSpacing.0}",
            "paragraphIndent": "{paragraphIndent.0}",
            "textCase": "{textCase.none}",
            "textDecoration": "{textDecoration.none}"
          },
          "type": "typography"
        },
        "lg": {
          "value": {
            "fontFamily": "{fontFamilies.riforma-ll}",
            "fontWeight": "{fontWeights.riforma-ll-0}",
            "lineHeight": "{lineHeights.1}",
            "fontSize": "{fontSize.5}",
            "letterSpacing": "{letterSpacing.1}",
            "paragraphSpacing": "{paragraphSpacing.0}",
            "paragraphIndent": "{paragraphIndent.0}",
            "textCase": "{textCase.none}",
            "textDecoration": "{textDecoration.none}"
          },
          "type": "typography"
        },
        "md": {
          "value": {
            "fontFamily": "{fontFamilies.riforma-ll}",
            "fontWeight": "{fontWeights.riforma-ll-1}",
            "lineHeight": "{lineHeights.1}",
            "fontSize": "{fontSize.4}",
            "letterSpacing": "{letterSpacing.1}",
            "paragraphSpacing": "{paragraphSpacing.0}",
            "paragraphIndent": "{paragraphIndent.0}",
            "textCase": "{textCase.none}",
            "textDecoration": "{textDecoration.none}"
          },
          "type": "typography"
        },
        "sm": {
          "value": {
            "fontFamily": "{fontFamilies.riforma-ll}",
            "fontWeight": "{fontWeights.riforma-ll-2}",
            "lineHeight": "{lineHeights.1}",
            "fontSize": "{fontSize.3}",
            "letterSpacing": "{letterSpacing.1}",
            "paragraphSpacing": "{paragraphSpacing.0}",
            "paragraphIndent": "{paragraphIndent.0}",
            "textCase": "{textCase.none}",
            "textDecoration": "{textDecoration.none}"
          },
          "type": "typography"
        },
        "xs": {
          "value": {
            "fontFamily": "{fontFamilies.riforma-ll}",
            "fontWeight": "{fontWeights.riforma-ll-3}",
            "lineHeight": "{lineHeights.1}",
            "fontSize": "{fontSize.0}",
            "letterSpacing": "{letterSpacing.1}",
            "paragraphSpacing": "{paragraphSpacing.0}",
            "paragraphIndent": "{paragraphIndent.0}",
            "textCase": "{textCase.none}",
            "textDecoration": "{textDecoration.none}"
          },
          "type": "typography"
        }
      },
      "body": {
        "xl": {
          "value": {
            "fontFamily": "{fontFamilies.riforma-ll}",
            "fontWeight": "{fontWeights.riforma-ll-1}",
            "lineHeight": "{lineHeights.1}",
            "fontSize": "{fontSize.4}",
            "letterSpacing": "{letterSpacing.1}",
            "paragraphSpacing": "{paragraphSpacing.0}",
            "paragraphIndent": "{paragraphIndent.0}",
            "textCase": "{textCase.none}",
            "textDecoration": "{textDecoration.none}"
          },
          "type": "typography"
        },
        "md": {
          "value": {
            "fontFamily": "{fontFamilies.riforma-ll}",
            "fontWeight": "{fontWeights.riforma-ll-1}",
            "lineHeight": "{lineHeights.1}",
            "fontSize": "{fontSize.2}",
            "letterSpacing": "{letterSpacing.1}",
            "paragraphSpacing": "{paragraphSpacing.0}",
            "paragraphIndent": "{paragraphIndent.0}",
            "textCase": "{textCase.none}",
            "textDecoration": "{textDecoration.none}"
          },
          "type": "typography"
        },
        "sm": {
          "value": {
            "fontFamily": "{fontFamilies.riforma-ll}",
            "fontWeight": "{fontWeights.riforma-ll-0}",
            "lineHeight": "{lineHeights.1}",
            "fontSize": "{fontSize.1}",
            "letterSpacing": "{letterSpacing.1}",
            "paragraphSpacing": "{paragraphSpacing.0}",
            "paragraphIndent": "{paragraphIndent.0}",
            "textCase": "{textCase.none}",
            "textDecoration": "{textDecoration.none}"
          },
          "type": "typography"
        }
      },
      "btn": {
        "lg": {
          "value": {
            "fontFamily": "{fontFamilies.riforma-ll}",
            "fontWeight": "{fontWeights.riforma-ll-2}",
            "lineHeight": "{lineHeights.1}",
            "fontSize": "{fontSize.4}",
            "letterSpacing": "{letterSpacing.1}",
            "paragraphSpacing": "{paragraphSpacing.0}",
            "paragraphIndent": "{paragraphIndent.0}",
            "textCase": "{textCase.none}",
            "textDecoration": "{textDecoration.none}"
          },
          "type": "typography"
        },
        "md": {
          "value": {
            "fontFamily": "{fontFamilies.riforma-ll}",
            "fontWeight": "{fontWeights.riforma-ll-2}",
            "lineHeight": "{lineHeights.1}",
            "fontSize": "{fontSize.2}",
            "letterSpacing": "{letterSpacing.2}",
            "paragraphSpacing": "{paragraphSpacing.0}",
            "paragraphIndent": "{paragraphIndent.0}",
            "textCase": "{textCase.none}",
            "textDecoration": "{textDecoration.none}"
          },
          "type": "typography"
        },
        "sm": {
          "value": {
            "fontFamily": "{fontFamilies.riforma-ll}",
            "fontWeight": "{fontWeights.riforma-ll-2}",
            "lineHeight": "{lineHeights.1}",
            "fontSize": "{fontSize.1}",
            "letterSpacing": "{letterSpacing.1}",
            "paragraphSpacing": "{paragraphSpacing.0}",
            "paragraphIndent": "{paragraphIndent.0}",
            "textCase": "{textCase.none}",
            "textDecoration": "{textDecoration.none}"
          },
          "type": "typography"
        }
      },
      "link": {
        "sm": {
          "value": {
            "fontFamily": "{fontFamilies.riforma-ll}",
            "fontWeight": "{fontWeights.riforma-ll-2}",
            "lineHeight": "{lineHeights.1}",
            "fontSize": "{fontSize.0}",
            "letterSpacing": "{letterSpacing.1}",
            "paragraphSpacing": "{paragraphSpacing.0}",
            "paragraphIndent": "{paragraphIndent.0}",
            "textCase": "{textCase.none}",
            "textDecoration": "{textDecoration.none}"
          },
          "type": "typography"
        }
      }
    },
    "MD Breakpoint": {
      "heading": {
        "xxl": {
          "value": {
            "fontFamily": "{fontFamilies.riforma-ll}",
            "fontWeight": "{fontWeights.riforma-ll-0}",
            "lineHeight": "{lineHeights.0}",
            "fontSize": "{fontSize.7}",
            "letterSpacing": "{letterSpacing.0}",
            "paragraphSpacing": "{paragraphSpacing.0}",
            "paragraphIndent": "{paragraphIndent.0}",
            "textCase": "{textCase.none}",
            "textDecoration": "{textDecoration.none}"
          },
          "type": "typography"
        },
        "xl": {
          "value": {
            "fontFamily": "{fontFamilies.riforma-ll}",
            "fontWeight": "{fontWeights.riforma-ll-0}",
            "lineHeight": "{lineHeights.0}",
            "fontSize": "{fontSize.6}",
            "letterSpacing": "{letterSpacing.0}",
            "paragraphSpacing": "{paragraphSpacing.0}",
            "paragraphIndent": "{paragraphIndent.0}",
            "textCase": "{textCase.none}",
            "textDecoration": "{textDecoration.none}"
          },
          "type": "typography"
        },
        "lg": {
          "value": {
            "fontFamily": "{fontFamilies.riforma-ll}",
            "fontWeight": "{fontWeights.riforma-ll-0}",
            "lineHeight": "{lineHeights.1}",
            "fontSize": "{fontSize.5}",
            "letterSpacing": "{letterSpacing.1}",
            "paragraphSpacing": "{paragraphSpacing.0}",
            "paragraphIndent": "{paragraphIndent.0}",
            "textCase": "{textCase.none}",
            "textDecoration": "{textDecoration.none}"
          },
          "type": "typography"
        },
        "md": {
          "value": {
            "fontFamily": "{fontFamilies.riforma-ll}",
            "fontWeight": "{fontWeights.riforma-ll-1}",
            "lineHeight": "{lineHeights.1}",
            "fontSize": "{fontSize.3}",
            "letterSpacing": "{letterSpacing.1}",
            "paragraphSpacing": "{paragraphSpacing.0}",
            "paragraphIndent": "{paragraphIndent.0}",
            "textCase": "{textCase.none}",
            "textDecoration": "{textDecoration.none}"
          },
          "type": "typography"
        },
        "sm": {
          "value": {
            "fontFamily": "{fontFamilies.riforma-ll}",
            "fontWeight": "{fontWeights.riforma-ll-2}",
            "lineHeight": "{lineHeights.1}",
            "fontSize": "{fontSize.1}",
            "letterSpacing": "{letterSpacing.1}",
            "paragraphSpacing": "{paragraphSpacing.0}",
            "paragraphIndent": "{paragraphIndent.0}",
            "textCase": "{textCase.none}",
            "textDecoration": "{textDecoration.none}"
          },
          "type": "typography"
        },
        "xs": {
          "value": {
            "fontFamily": "{fontFamilies.riforma-ll}",
            "fontWeight": "{fontWeights.riforma-ll-3}",
            "lineHeight": "{lineHeights.1}",
            "fontSize": "{fontSize.0}",
            "letterSpacing": "{letterSpacing.1}",
            "paragraphSpacing": "{paragraphSpacing.0}",
            "paragraphIndent": "{paragraphIndent.0}",
            "textCase": "{textCase.none}",
            "textDecoration": "{textDecoration.none}"
          },
          "type": "typography"
        }
      },
      "body": {
        "xl": {
          "value": {
            "fontFamily": "{fontFamilies.riforma-ll}",
            "fontWeight": "{fontWeights.riforma-ll-1}",
            "lineHeight": "{lineHeights.1}",
            "fontSize": "{fontSize.3}",
            "letterSpacing": "{letterSpacing.1}",
            "paragraphSpacing": "{paragraphSpacing.0}",
            "paragraphIndent": "{paragraphIndent.0}",
            "textCase": "{textCase.none}",
            "textDecoration": "{textDecoration.none}"
          },
          "type": "typography"
        },
        "md": {
          "value": {
            "fontFamily": "{fontFamilies.riforma-ll}",
            "fontWeight": "{fontWeights.riforma-ll-1}",
            "lineHeight": "{lineHeights.1}",
            "fontSize": "{fontSize.2}",
            "letterSpacing": "{letterSpacing.1}",
            "paragraphSpacing": "{paragraphSpacing.0}",
            "paragraphIndent": "{paragraphIndent.0}",
            "textCase": "{textCase.none}",
            "textDecoration": "{textDecoration.none}"
          },
          "type": "typography"
        },
        "sm": {
          "value": {
            "fontFamily": "{fontFamilies.riforma-ll}",
            "fontWeight": "{fontWeights.riforma-ll-0}",
            "lineHeight": "{lineHeights.1}",
            "fontSize": "{fontSize.1}",
            "letterSpacing": "{letterSpacing.1}",
            "paragraphSpacing": "{paragraphSpacing.0}",
            "paragraphIndent": "{paragraphIndent.0}",
            "textCase": "{textCase.none}",
            "textDecoration": "{textDecoration.none}"
          },
          "type": "typography"
        }
      },
      "link": {
        "sm": {
          "value": {
            "fontFamily": "{fontFamilies.riforma-ll}",
            "fontWeight": "{fontWeights.riforma-ll-2}",
            "lineHeight": "{lineHeights.1}",
            "fontSize": "{fontSize.0}",
            "letterSpacing": "{letterSpacing.1}",
            "paragraphSpacing": "{paragraphSpacing.0}",
            "paragraphIndent": "{paragraphIndent.0}",
            "textCase": "{textCase.none}",
            "textDecoration": "{textDecoration.none}"
          },
          "type": "typography"
        }
      },
      "btn": {
        "md": {
          "value": {
            "fontFamily": "{fontFamilies.riforma-ll}",
            "fontWeight": "{fontWeights.riforma-ll-2}",
            "lineHeight": "{lineHeights.1}",
            "fontSize": "{fontSize.1}",
            "letterSpacing": "{letterSpacing.2}",
            "paragraphSpacing": "{paragraphSpacing.0}",
            "paragraphIndent": "{paragraphIndent.0}",
            "textCase": "{textCase.none}",
            "textDecoration": "{textDecoration.none}"
          },
          "type": "typography"
        }
      }
    },
    "SM Breakpoint": {
      "heading": {
        "xxl": {
          "value": {
            "fontFamily": "{fontFamilies.riforma-ll}",
            "fontWeight": "{fontWeights.riforma-ll-0}",
            "lineHeight": "{lineHeights.0}",
            "fontSize": "{fontSize.6}",
            "letterSpacing": "{letterSpacing.0}",
            "paragraphSpacing": "{paragraphSpacing.0}",
            "paragraphIndent": "{paragraphIndent.0}",
            "textCase": "{textCase.none}",
            "textDecoration": "{textDecoration.none}"
          },
          "type": "typography"
        },
        "xl": {
          "value": {
            "fontFamily": "{fontFamilies.riforma-ll}",
            "fontWeight": "{fontWeights.riforma-ll-0}",
            "lineHeight": "{lineHeights.0}",
            "fontSize": "{fontSize.5}",
            "letterSpacing": "{letterSpacing.0}",
            "paragraphSpacing": "{paragraphSpacing.0}",
            "paragraphIndent": "{paragraphIndent.0}",
            "textCase": "{textCase.none}",
            "textDecoration": "{textDecoration.none}"
          },
          "type": "typography"
        },
        "lg": {
          "value": {
            "fontFamily": "{fontFamilies.riforma-ll}",
            "fontWeight": "{fontWeights.riforma-ll-0}",
            "lineHeight": "{lineHeights.1}",
            "fontSize": "{fontSize.4}",
            "letterSpacing": "{letterSpacing.1}",
            "paragraphSpacing": "{paragraphSpacing.0}",
            "paragraphIndent": "{paragraphIndent.0}",
            "textCase": "{textCase.none}",
            "textDecoration": "{textDecoration.none}"
          },
          "type": "typography"
        },
        "md": {
          "value": {
            "fontFamily": "{fontFamilies.riforma-ll}",
            "fontWeight": "{fontWeights.riforma-ll-1}",
            "lineHeight": "{lineHeights.1}",
            "fontSize": "{fontSize.3}",
            "letterSpacing": "{letterSpacing.1}",
            "paragraphSpacing": "{paragraphSpacing.0}",
            "paragraphIndent": "{paragraphIndent.0}",
            "textCase": "{textCase.none}",
            "textDecoration": "{textDecoration.none}"
          },
          "type": "typography"
        },
        "sm": {
          "value": {
            "fontFamily": "{fontFamilies.riforma-ll}",
            "fontWeight": "{fontWeights.riforma-ll-2}",
            "lineHeight": "{lineHeights.1}",
            "fontSize": "{fontSize.2}",
            "letterSpacing": "{letterSpacing.1}",
            "paragraphSpacing": "{paragraphSpacing.0}",
            "paragraphIndent": "{paragraphIndent.0}",
            "textCase": "{textCase.none}",
            "textDecoration": "{textDecoration.none}"
          },
          "type": "typography"
        },
        "xs": {
          "value": {
            "fontFamily": "{fontFamilies.riforma-ll}",
            "fontWeight": "{fontWeights.riforma-ll-3}",
            "lineHeight": "{lineHeights.1}",
            "fontSize": "{fontSize.0}",
            "letterSpacing": "{letterSpacing.1}",
            "paragraphSpacing": "{paragraphSpacing.0}",
            "paragraphIndent": "{paragraphIndent.0}",
            "textCase": "{textCase.none}",
            "textDecoration": "{textDecoration.none}"
          },
          "type": "typography"
        }
      },
      "body": {
        "xl": {
          "value": {
            "fontFamily": "{fontFamilies.riforma-ll}",
            "fontWeight": "{fontWeights.riforma-ll-1}",
            "lineHeight": "{lineHeights.1}",
            "fontSize": "{fontSize.3}",
            "letterSpacing": "{letterSpacing.1}",
            "paragraphSpacing": "{paragraphSpacing.0}",
            "paragraphIndent": "{paragraphIndent.0}",
            "textCase": "{textCase.none}",
            "textDecoration": "{textDecoration.none}"
          },
          "type": "typography"
        },
        "md": {
          "value": {
            "fontFamily": "{fontFamilies.riforma-ll}",
            "fontWeight": "{fontWeights.riforma-ll-1}",
            "lineHeight": "{lineHeights.1}",
            "fontSize": "{fontSize.2}",
            "letterSpacing": "{letterSpacing.1}",
            "paragraphSpacing": "{paragraphSpacing.0}",
            "paragraphIndent": "{paragraphIndent.0}",
            "textCase": "{textCase.none}",
            "textDecoration": "{textDecoration.none}"
          },
          "type": "typography"
        },
        "sm": {
          "value": {
            "fontFamily": "{fontFamilies.riforma-ll}",
            "fontWeight": "{fontWeights.riforma-ll-0}",
            "lineHeight": "{lineHeights.1}",
            "fontSize": "{fontSize.1}",
            "letterSpacing": "{letterSpacing.1}",
            "paragraphSpacing": "{paragraphSpacing.0}",
            "paragraphIndent": "{paragraphIndent.0}",
            "textCase": "{textCase.none}",
            "textDecoration": "{textDecoration.none}"
          },
          "type": "typography"
        }
      },
      "btn": {
        "lg": {
          "value": {
            "fontFamily": "{fontFamilies.riforma-ll}",
            "fontWeight": "{fontWeights.riforma-ll-2}",
            "lineHeight": "{lineHeights.1}",
            "fontSize": "{fontSize.4}",
            "letterSpacing": "{letterSpacing.1}",
            "paragraphSpacing": "{paragraphSpacing.0}",
            "paragraphIndent": "{paragraphIndent.0}",
            "textCase": "{textCase.none}",
            "textDecoration": "{textDecoration.none}"
          },
          "type": "typography"
        },
        "md": {
          "value": {
            "fontFamily": "{fontFamilies.riforma-ll}",
            "fontWeight": "{fontWeights.riforma-ll-2}",
            "lineHeight": "{lineHeights.1}",
            "fontSize": "{fontSize.2}",
            "letterSpacing": "{letterSpacing.2}",
            "paragraphSpacing": "{paragraphSpacing.0}",
            "paragraphIndent": "{paragraphIndent.0}",
            "textCase": "{textCase.none}",
            "textDecoration": "{textDecoration.none}"
          },
          "type": "typography"
        },
        "sm": {
          "value": {
            "fontFamily": "{fontFamilies.riforma-ll}",
            "fontWeight": "{fontWeights.riforma-ll-2}",
            "lineHeight": "{lineHeights.1}",
            "fontSize": "{fontSize.1}",
            "letterSpacing": "{letterSpacing.1}",
            "paragraphSpacing": "{paragraphSpacing.0}",
            "paragraphIndent": "{paragraphIndent.0}",
            "textCase": "{textCase.none}",
            "textDecoration": "{textDecoration.none}"
          },
          "type": "typography"
        }
      },
      "link": {
        "sm": {
          "value": {
            "fontFamily": "{fontFamilies.riforma-ll}",
            "fontWeight": "{fontWeights.riforma-ll-2}",
            "lineHeight": "{lineHeights.1}",
            "fontSize": "{fontSize.0}",
            "letterSpacing": "{letterSpacing.1}",
            "paragraphSpacing": "{paragraphSpacing.0}",
            "paragraphIndent": "{paragraphIndent.0}",
            "textCase": "{textCase.none}",
            "textDecoration": "{textDecoration.none}"
          },
          "type": "typography"
        }
      }
    }
  },
  "Mode/Light": {
    "text": {
      "onbase": {
        "primary": {
          "value": "{core.neutral.900}",
          "type": "color"
        },
        "secondary": {
          "value": "{core.neutral.700}",
          "type": "color"
        },
        "accent": {
          "value": "{core.red.500}",
          "type": "color"
        },
        "disabled": {
          "value": "{core.neutral.500}",
          "type": "color"
        }
      },
      "inverse": {
        "primary": {
          "value": "{core.neutral.50}",
          "type": "color"
        },
        "secondary": {
          "value": "{core.neutral.200}",
          "type": "color"
        },
        "accent": {
          "value": "{core.red.400}",
          "type": "color"
        }
      },
      "onsubtle": {
        "primary": {
          "value": "{core.neutral.900}",
          "type": "color"
        },
        "secondary": {
          "value": "{core.neutral.700}",
          "type": "color"
        },
        "accent": {
          "value": "{core.red.500}",
          "type": "color"
        },
        "disabled": {
          "value": "{core.neutral.500}",
          "type": "color"
        }
      },
      "onaccent": {
        "primary": {
          "value": "{core.neutral.900}",
          "type": "color"
        },
        "secondary": {
          "value": "{core.neutral.700}",
          "type": "color"
        },
        "disabled": {
          "value": "{core.neutral.500}",
          "type": "color"
        }
      },
      "onbrand": {
        "primary": {
          "value": "{core.neutral.50}",
          "type": "color"
        }
      },
      "ondisabled": {
        "primary": {
          "value": "{core.neutral.50}",
          "type": "color"
        },
        "secondary": {
          "value": "{core.neutral.500}",
          "type": "color"
        }
      }
    },
    "background": {
      "base": {
        "value": "{core.neutral.50}",
        "type": "color"
      },
      "subtle": {
        "value": "{core.neutral.100}",
        "type": "color"
      },
      "accent": {
        "value": "{core.red.100}",
        "type": "color"
      },
      "inverse": {
        "value": "{core.neutral.900}",
        "type": "color"
      }
    },
    "primary-action": {
      "default": {
        "value": "{core.neutral.900}",
        "type": "color"
      },
      "hover": {
        "value": "{core.red.500}",
        "type": "color"
      },
      "active": {
        "value": "{core.red.600}",
        "type": "color"
      },
      "focus": {
        "value": "{core.red.500}",
        "type": "color"
      },
      "disabled": {
        "value": "{core.neutral.500}",
        "type": "color"
      }
    },
    "secondary-action": {
      "default": {
        "value": "{core.neutral.900}",
        "type": "color"
      },
      "hover": {
        "value": "{core.red.500}",
        "type": "color"
      },
      "active": {
        "value": "{core.red.600}",
        "type": "color"
      },
      "focus": {
        "value": "{core.red.500}",
        "type": "color"
      },
      "disabled": {
        "value": "{core.neutral.500}",
        "type": "color"
      }
    }
  },
  "Mode/Dark": {},
  "Breakpoint/Large": {
    "heading": {
      "xxl": {
        "value": {
          "fontFamily": "{fontFamilies.default}",
          "fontWeight": "{fontWeight.bold}",
          "lineHeight": "{lineHeights.tight}",
          "fontSize": "{fontSize.1000}",
          "letterSpacing": "{letterSpacing.xtr-tight}",
          "paragraphSpacing": "",
          "paragraphIndent": "",
          "textCase": "",
          "textDecoration": ""
        },
        "type": "typography"
      },
      "xl": {
        "value": {
          "fontFamily": "{fontFamilies.default}",
          "fontWeight": "{fontWeight.bold}",
          "lineHeight": "{lineHeights.tight}",
          "fontSize": "{fontSize.800}",
          "letterSpacing": "{letterSpacing.xtr-tight}",
          "paragraphSpacing": "",
          "paragraphIndent": "",
          "textCase": "",
          "textDecoration": ""
        },
        "type": "typography"
      },
      "lg": {
        "value": {
          "fontFamily": "{fontFamilies.default}",
          "fontWeight": "{fontWeight.bold}",
          "lineHeight": "{lineHeights.regular}",
          "fontSize": "{fontSize.700}",
          "letterSpacing": "{letterSpacing.regular}"
        },
        "type": "typography"
      },
      "md": {
        "value": {
          "fontFamily": "{fontFamilies.default}",
          "fontWeight": "{fontWeight.reg}",
          "lineHeight": "{lineHeights.regular}",
          "fontSize": "{fontSize.600}",
          "letterSpacing": "{letterSpacing.regular}",
          "paragraphSpacing": "",
          "paragraphIndent": "",
          "textCase": "",
          "textDecoration": ""
        },
        "type": "typography"
      },
      "sm": {
        "value": {
          "fontFamily": "{fontFamilies.default}",
          "fontWeight": "{fontWeight.med}",
          "lineHeight": "{lineHeights.regular}",
          "fontSize": "{fontSize.500}",
          "letterSpacing": "{letterSpacing.regular}",
          "paragraphSpacing": "",
          "paragraphIndent": "",
          "textCase": "",
          "textDecoration": ""
        },
        "type": "typography"
      },
      "xs": {
        "value": {
          "fontFamily": "{fontFamilies.default}",
          "fontWeight": "{fontWeight.lt}",
          "lineHeight": "{lineHeights.regular}",
          "fontSize": "{fontSize.200}",
          "letterSpacing": "{letterSpacing.regular}"
        },
        "type": "typography"
      }
    },
    "body": {
      "xl": {
        "value": {
          "fontFamily": "{fontFamilies.default}",
          "fontWeight": "{fontWeight.reg}",
          "lineHeight": "{lineHeights.regular}",
          "fontSize": "{fontSize.600}",
          "letterSpacing": "{letterSpacing.regular}",
          "paragraphSpacing": "",
          "paragraphIndent": "",
          "textCase": "",
          "textDecoration": ""
        },
        "type": "typography"
      },
      "md": {
        "value": {
          "fontFamily": "{fontFamilies.default}",
          "fontWeight": "{fontWeight.reg}",
          "lineHeight": "{lineHeights.regular}",
          "fontSize": "{fontSize.400}",
          "letterSpacing": "{letterSpacing.regular}",
          "paragraphSpacing": "",
          "paragraphIndent": "",
          "textCase": "",
          "textDecoration": ""
        },
        "type": "typography"
      },
      "sm": {
        "value": {
          "fontFamily": "{fontFamilies.default}",
          "fontWeight": "{fontWeight.reg}",
          "lineHeight": "{lineHeights.regular}",
          "fontSize": "{fontSize.300}",
          "letterSpacing": "{letterSpacing.regular}"
        },
        "type": "typography"
      }
    },
    "link": {
      "sm": {
        "value": {
          "fontFamily": "{fontFamilies.default}",
          "fontWeight": "{fontWeight.med}",
          "lineHeight": "{lineHeights.regular}",
          "fontSize": "{fontSize.200}",
          "letterSpacing": "{letterSpacing.regular}",
          "paragraphSpacing": "",
          "paragraphIndent": "",
          "textCase": "",
          "textDecoration": ""
        },
        "type": "typography"
      }
    },
    "btn": {
      "md": {
        "value": {
          "fontFamily": "{fontFamilies.default}",
          "fontWeight": "{fontWeight.med}",
          "lineHeight": "{lineHeights.regular}",
          "fontSize": "{fontSize.300}",
          "letterSpacing": "{letterSpacing.loose}",
          "paragraphSpacing": "",
          "paragraphIndent": "",
          "textCase": "",
          "textDecoration": "{textDecoration.none}"
        },
        "type": "typography"
      }
    }
  },
  "Breakpoint/Medium": {
    "heading": {
      "xxl": {
        "value": {
          "fontFamily": "{fontFamilies.default}",
          "fontWeight": "{fontWeight.bold}",
          "lineHeight": "{lineHeights.tight}",
          "fontSize": "{fontSize.900}",
          "letterSpacing": "{letterSpacing.xtr-tight}",
          "paragraphSpacing": "",
          "paragraphIndent": "",
          "textCase": "",
          "textDecoration": ""
        },
        "type": "typography"
      },
      "xl": {
        "value": {
          "fontFamily": "{fontFamilies.default}",
          "fontWeight": "{fontWeight.bold}",
          "lineHeight": "{lineHeights.tight}",
          "fontSize": "{fontSize.800}",
          "letterSpacing": "{letterSpacing.xtr-tight}",
          "paragraphSpacing": "",
          "paragraphIndent": "",
          "textCase": "",
          "textDecoration": ""
        },
        "type": "typography"
      },
      "lg": {
        "value": {
          "fontFamily": "{fontFamilies.default}",
          "fontWeight": "{fontWeight.bold}",
          "lineHeight": "{lineHeights.regular}",
          "fontSize": "{fontSize.700}",
          "letterSpacing": "{letterSpacing.regular}"
        },
        "type": "typography"
      },
      "md": {
        "value": {
          "fontFamily": "{fontFamilies.default}",
          "fontWeight": "{fontWeight.reg}",
          "lineHeight": "{lineHeights.regular}",
          "fontSize": "{fontSize.500}",
          "letterSpacing": "{letterSpacing.regular}",
          "paragraphSpacing": "",
          "paragraphIndent": "",
          "textCase": "",
          "textDecoration": ""
        },
        "type": "typography"
      },
      "sm": {
        "value": {
          "fontFamily": "{fontFamilies.default}",
          "fontWeight": "{fontWeight.med}",
          "lineHeight": "{lineHeights.regular}",
          "fontSize": "{fontSize.400}",
          "letterSpacing": "{letterSpacing.regular}",
          "paragraphSpacing": "",
          "paragraphIndent": "",
          "textCase": "",
          "textDecoration": ""
        },
        "type": "typography"
      },
      "xs": {
        "value": {
          "fontFamily": "{fontFamilies.default}",
          "fontWeight": "{fontWeight.lt}",
          "lineHeight": "{lineHeights.regular}",
          "fontSize": "{fontSize.200}",
          "letterSpacing": "{letterSpacing.regular}"
        },
        "type": "typography"
      }
    },
    "body": {
      "xl": {
        "value": {
          "fontFamily": "{fontFamilies.default}",
          "fontWeight": "{fontWeight.reg}",
          "lineHeight": "{lineHeights.regular}",
          "fontSize": "{fontSize.500}",
          "letterSpacing": "{letterSpacing.regular}",
          "paragraphSpacing": "",
          "paragraphIndent": "",
          "textCase": "",
          "textDecoration": ""
        },
        "type": "typography"
      },
      "md": {
        "value": {
          "fontFamily": "{fontFamilies.default}",
          "fontWeight": "{fontWeight.reg}",
          "lineHeight": "{lineHeights.regular}",
          "fontSize": "{fontSize.400}",
          "letterSpacing": "{letterSpacing.regular}",
          "paragraphSpacing": "",
          "paragraphIndent": "",
          "textCase": "",
          "textDecoration": ""
        },
        "type": "typography"
      },
      "sm": {
        "value": {
          "fontFamily": "{fontFamilies.default}",
          "fontWeight": "{fontWeight.reg}",
          "lineHeight": "{lineHeights.regular}",
          "fontSize": "{fontSize.300}",
          "letterSpacing": "{letterSpacing.regular}"
        },
        "type": "typography"
      }
    },
    "link": {
      "sm": {
        "value": {
          "fontFamily": "{fontFamilies.default}",
          "fontWeight": "{fontWeight.med}",
          "lineHeight": "{lineHeights.regular}",
          "fontSize": "{fontSize.200}",
          "letterSpacing": "{letterSpacing.regular}",
          "paragraphSpacing": "",
          "paragraphIndent": "",
          "textCase": "",
          "textDecoration": ""
        },
        "type": "typography"
      }
    },
    "btn": {
      "md": {
        "value": {
          "fontFamily": "{fontFamilies.default}",
          "fontWeight": "{fontWeight.med}",
          "lineHeight": "{lineHeights.regular}",
          "fontSize": "{fontSize.300}",
          "letterSpacing": "{letterSpacing.loose}",
          "paragraphSpacing": "",
          "paragraphIndent": "",
          "textCase": "",
          "textDecoration": "{textDecoration.none}"
        },
        "type": "typography"
      }
    }
  },
  "Breakpoint/Small": {
    "heading": {
      "xxl": {
        "value": {
          "fontFamily": "{fontFamilies.default}",
          "fontWeight": "{fontWeight.bold}",
          "lineHeight": "{lineHeights.tight}",
          "fontSize": "{fontSize.800}",
          "letterSpacing": "{letterSpacing.xtr-tight}",
          "paragraphSpacing": "",
          "paragraphIndent": "",
          "textCase": "",
          "textDecoration": ""
        },
        "type": "typography"
      },
      "xl": {
        "value": {
          "fontFamily": "{fontFamilies.default}",
          "fontWeight": "{fontWeight.bold}",
          "lineHeight": "{lineHeights.tight}",
          "fontSize": "{fontSize.700}",
          "letterSpacing": "{letterSpacing.xtr-tight}",
          "paragraphSpacing": "",
          "paragraphIndent": "",
          "textCase": "",
          "textDecoration": ""
        },
        "type": "typography"
      },
      "lg": {
        "value": {
          "fontFamily": "{fontFamilies.default}",
          "fontWeight": "{fontWeight.bold}",
          "lineHeight": "{lineHeights.regular}",
          "fontSize": "{fontSize.600}",
          "letterSpacing": "{letterSpacing.regular}"
        },
        "type": "typography"
      },
      "md": {
        "value": {
          "fontFamily": "{fontFamilies.default}",
          "fontWeight": "{fontWeight.reg}",
          "lineHeight": "{lineHeights.regular}",
          "fontSize": "{fontSize.500}",
          "letterSpacing": "{letterSpacing.regular}",
          "paragraphSpacing": "",
          "paragraphIndent": "",
          "textCase": "",
          "textDecoration": ""
        },
        "type": "typography"
      },
      "sm": {
        "value": {
          "fontFamily": "{fontFamilies.default}",
          "fontWeight": "{fontWeight.med}",
          "lineHeight": "{lineHeights.regular}",
          "fontSize": "{fontSize.400}",
          "letterSpacing": "{letterSpacing.regular}",
          "paragraphSpacing": "",
          "paragraphIndent": "",
          "textCase": "",
          "textDecoration": ""
        },
        "type": "typography"
      },
      "xs": {
        "value": {
          "fontFamily": "{fontFamilies.default}",
          "fontWeight": "{fontWeight.lt}",
          "lineHeight": "{lineHeights.regular}",
          "fontSize": "{fontSize.200}",
          "letterSpacing": "{letterSpacing.regular}"
        },
        "type": "typography"
      }
    },
    "body": {
      "xl": {
        "value": {
          "fontFamily": "{fontFamilies.default}",
          "fontWeight": "{fontWeight.reg}",
          "lineHeight": "{lineHeights.regular}",
          "fontSize": "{fontSize.500}",
          "letterSpacing": "{letterSpacing.regular}",
          "paragraphSpacing": "",
          "paragraphIndent": "",
          "textCase": "",
          "textDecoration": ""
        },
        "type": "typography"
      },
      "md": {
        "value": {
          "fontFamily": "{fontFamilies.default}",
          "fontWeight": "{fontWeight.reg}",
          "lineHeight": "{lineHeights.regular}",
          "fontSize": "{fontSize.400}",
          "letterSpacing": "{letterSpacing.regular}",
          "paragraphSpacing": "",
          "paragraphIndent": "",
          "textCase": "",
          "textDecoration": ""
        },
        "type": "typography"
      },
      "sm": {
        "value": {
          "fontFamily": "{fontFamilies.default}",
          "fontWeight": "{fontWeight.reg}",
          "lineHeight": "{lineHeights.regular}",
          "fontSize": "{fontSize.300}",
          "letterSpacing": "{letterSpacing.regular}"
        },
        "type": "typography"
      }
    },
    "link": {
      "sm": {
        "value": {
          "fontFamily": "{fontFamilies.default}",
          "fontWeight": "{fontWeight.med}",
          "lineHeight": "{lineHeights.regular}",
          "fontSize": "{fontSize.200}",
          "letterSpacing": "{letterSpacing.regular}",
          "paragraphSpacing": "",
          "paragraphIndent": "",
          "textCase": "",
          "textDecoration": ""
        },
        "type": "typography"
      }
    },
    "btn": {
      "md": {
        "value": {
          "fontFamily": "{fontFamilies.default}",
          "fontWeight": "{fontWeight.med}",
          "lineHeight": "{lineHeights.regular}",
          "fontSize": "{fontSize.300}",
          "letterSpacing": "{letterSpacing.loose}",
          "paragraphSpacing": "",
          "paragraphIndent": "",
          "textCase": "",
          "textDecoration": "{textDecoration.none}"
        },
        "type": "typography"
      }
    }
  },
  "Components/Components": {},
  "$themes": [],
  "$metadata": {
    "tokenSetOrder": [
      "core",
      "Brand/Radius",
      "Mode/Light",
      "Mode/Dark",
      "Breakpoint/Large",
      "Breakpoint/Medium",
      "Breakpoint/Small",
      "Components/Components"
    ]
  }
}